setup.py
na3x/__init__.py
na3x/cfg.py
na3x.egg-info/PKG-INFO
na3x.egg-info/SOURCES.txt
na3x.egg-info/dependency_links.txt
na3x.egg-info/requires.txt
na3x.egg-info/top_level.txt
na3x/data/__init__.py
na3x/data/generator.py
na3x/db/__init__.py
na3x/db/connect.py
na3x/db/data.py
na3x/integration/__init__.py
na3x/integration/exporter.py
na3x/integration/importer.py
na3x/integration/integrator.py
na3x/integration/request.py
na3x/transformation/__init__.py
na3x/transformation/transformer.py
na3x/utils/__init__.py
na3x/utils/aggregator.py
na3x/utils/cfg.py
na3x/utils/converter.py
na3x/utils/json.py
na3x/utils/object.py
na3x/validation/__init__.py
na3x/validation/validator.py