Metadata-Version: 1.2
Name: na3x
Version: 0.1.5
Summary: na3x data transformation and integration framework
Home-page: https://github.com/yero13/na3x
Author: Roman Yepifanov
Author-email: UNKNOWN
License: MIT
Platform: UNKNOWN
Classifier: Development Status :: 3 - Alpha
Classifier: Environment :: Console
Classifier: Programming Language :: Python :: 3.6
Requires-Python: ~=3.6
